[
  {
    "fid": -1534666,
    "name": "瓦斯琪尓水族馆",
    "cid": "other"
  },
  {
    "fid": 124,
    "name": "壁画洞窟",
    "cid": "other"
  },
  {
    "fid": -444012,
    "name": "我们的骑迹",
    "cid": "other"
  },
  {
    "fid": -522474,
    "name": "北京2022冬季奥运会",
    "cid": "other"
  },
  {
    "fid": 102,
    "name": "作家协会",
    "cid": "other"
  },
  {
    "fid": -4567100,
    "name": "狼人杀",
    "cid": "other"
  },
  {
    "fid": -349066,
    "name": "吟瑟梨茗",
    "cid": "other"
  },
  {
    "fid": -40639972,
    "name": "VOCALOID",
    "cid": "other"
  },
  {
    "fid": 485,
    "name": "篮球",
    "cid": "other"
  },
  {
    "fid": 716,
    "name": "模型手办",
    "cid": "other"
  },
  {
    "fid": -608808,
    "name": "弑熊主厨的血腥厨房",
    "cid": "other"
  },
  {
    "fid": -353371,
    "name": "萌萌宠物",
    "cid": "other"
  },
  {
    "fid": -7678526,
    "name": "麻将",
    "cid": "other"
  },
  {
    "fid": -187628,
    "name": "家居装修",
    "cid": "other"
  },
  {
    "fid": -8725919,
    "name": "小窗视界",
    "cid": "other"
  },
  {
    "fid": -39223361,
    "name": "娱乐吃瓜区",
    "cid": "other"
  },
  {
    "fid": -2671,
    "name": "发烧友",
    "cid": "other"
  },
  {
    "fid": 761,
    "name": "桌游讨论",
    "cid": "other"
  },
  {
    "fid": -7,
    "name": "网事杂谈",
    "cid": "other"
  },
  {
    "fid": 704,
    "name": "生活万象",
    "cid": "other"
  },
  {
    "fid": -7955747,
    "name": "晴风村",
    "cid": "other"
  },
  {
    "fid": -343809,
    "name": "寂寞的车",
    "cid": "other"
  },
  {
    "fid": -447601,
    "name": "二次元国家地理",
    "cid": "other"
  },
  {
    "fid": 706,
    "name": "大时代",
    "cid": "other"
  },
  {
    "fid": -576177,
    "name": "音乐影视",
    "cid": "other"
  },
  {
    "fid": 524,
    "name": "漩涡书院",
    "cid": "other"
  },
  {
    "fid": -1459709,
    "name": "职场人生",
    "cid": "other"
  },
  {
    "fid": -81981,
    "name": "生命之杯",
    "cid": "other"
  },
  {
    "fid": 767,
    "name": "剧本杀(谋杀之谜)",
    "cid": "other"
  },
  {
    "fid": -202020,
    "name": "程序员职业交流",
    "cid": "other"
  },
  {
    "fid": 436,
    "name": "消费电子 IT新闻",
    "cid": "other"
  },
  {
    "fid": 334,
    "name": "PC硬件配置",
    "cid": "other"
  },
  {
    "fid": 722,
    "name": "手机研究所",
    "cid": "other"
  },
  {
    "fid": 773,
    "name": "外设硬件",
    "cid": "other"
  },
  {
    "fid": 498,
    "name": "二手交易",
    "cid": "other"
  },
  {
    "fid": 459,
    "name": "守望先锋",
    "cid": "bliz"
  },
  {
    "fid": 422,
    "name": "炉石传说",
    "cid": "bliz"
  },
  {
    "fid": 318,
    "name": "暗黑破坏神3",
    "cid": "bliz"
  },
  {
    "fid": 431,
    "name": "风暴英雄",
    "cid": "bliz"
  },
  {
    "fid": 406,
    "name": "星际争霸2",
    "cid": "bliz"
  },
  {
    "fid": 490,
    "name": "魔兽争霸",
    "cid": "bliz"
  },
  {
    "fid": 685,
    "name": "暗黑破坏神4",
    "cid": "bliz"
  },
  {
    "fid": 769,
    "name": "暗黑破坏神2 重置版",
    "cid": "bliz"
  },
  {
    "fid": 631,
    "name": "暗黑破坏神:不朽",
    "cid": "bliz"
  },
  {
    "fid": 687,
    "name": "OVERWATCH2",
    "cid": "bliz"
  },
  {
    "fid": 632,
    "name": "2020暴雪嘉年华",
    "cid": "bliz"
  },
  {
    "fid": 7,
    "name": "议事厅",
    "cid": "wow"
  },
  {
    "fid": 230,
    "name": "风纪委员会",
    "cid": "wow"
  },
  {
    "fid": 310,
    "name": "前瞻资讯",
    "cid": "wow"
  },
  {
    "fid": 770,
    "name": "燃烧的远征",
    "cid": "wow"
  },
  {
    "fid": 624,
    "name": "经典旧世",
    "cid": "wow"
  },
  {
    "fid": 323,
    "name": "国服以外",
    "cid": "wow"
  },
  {
    "fid": 390,
    "name": "五晨寺",
    "cid": "wow"
  },
  {
    "fid": 477,
    "name": "伊利达雷",
    "cid": "wow"
  },
  {
    "fid": 320,
    "name": "黑锋要塞",
    "cid": "wow"
  },
  {
    "fid": 181,
    "name": "铁血沙场",
    "cid": "wow"
  },
  {
    "fid": 182,
    "name": "魔法圣堂",
    "cid": "wow"
  },
  {
    "fid": 183,
    "name": "信仰神殿",
    "cid": "wow"
  },
  {
    "fid": 185,
    "name": "风暴祭坛",
    "cid": "wow"
  },
  {
    "fid": 186,
    "name": "翡翠梦境",
    "cid": "wow"
  },
  {
    "fid": 187,
    "name": "猎手大厅",
    "cid": "wow"
  },
  {
    "fid": 184,
    "name": "圣光之力",
    "cid": "wow"
  },
  {
    "fid": 188,
    "name": "恶魔深渊",
    "cid": "wow"
  },
  {
    "fid": 189,
    "name": "暗影裂口",
    "cid": "wow"
  },
  {
    "fid": 200,
    "name": "插件研究",
    "cid": "wow"
  },
  {
    "fid": 240,
    "name": "魔兽世界大脚",
    "cid": "wow"
  },
  {
    "fid": 310,
    "name": "前瞻资讯",
    "cid": "wow"
  },
  {
    "fid": 463,
    "name": "要塞讨论",
    "cid": "wow"
  },
  {
    "fid": 327,
    "name": "任务/成就",
    "cid": "wow"
  },
  {
    "fid": 218,
    "name": "副本专区",
    "cid": "wow"
  },
  {
    "fid": 388,
    "name": "幻化讨论",
    "cid": "wow"
  },
  {
    "fid": 411,
    "name": "宠物讨论",
    "cid": "wow"
  },
  {
    "fid": 191,
    "name": "地精商会",
    "cid": "wow"
  },
  {
    "fid": 272,
    "name": "竞技场/战场",
    "cid": "wow"
  },
  {
    "fid": 213,
    "name": "战争档案",
    "cid": "wow"
  },
  {
    "fid": 255,
    "name": "公会管理",
    "cid": "wow"
  },
  {
    "fid": 306,
    "name": "人员招募",
    "cid": "wow"
  },
  {
    "fid": 254,
    "name": "镶金玫瑰",
    "cid": "wow"
  },
  {
    "fid": 124,
    "name": "壁画洞窟",
    "cid": "wow"
  },
  {
    "fid": 102,
    "name": "作家协会",
    "cid": "wow"
  },
  {
    "fid": 264,
    "name": "卡拉赞剧院",
    "cid": "wow"
  },
  {
    "fid": -152678,
    "name": "英雄联盟",
    "cid": "riot"
  },
  {
    "fid": 708,
    "name": "无畏契约",
    "cid": "riot"
  },
  {
    "fid": 660,
    "name": "LOL云顶之弈",
    "cid": "riot"
  },
  {
    "fid": 681,
    "name": "英雄联盟手游",
    "cid": "riot"
  },
  {
    "fid": 680,
    "name": "英雄联盟策略卡牌",
    "cid": "riot"
  },
  {
    "fid": 482,
    "name": "CS:GO",
    "cid": "valve"
  },
  {
    "fid": 321,
    "name": "DOTA2",
    "cid": "valve"
  },
  {
    "fid": 622,
    "name": "刀塔卡牌",
    "cid": "valve"
  },
  {
    "fid": 659,
    "name": "刀塔霸业",
    "cid": "valve"
  },
  {
    "fid": 591,
    "name": "格斗游戏综合",
    "cid": "games"
  },
  {
    "fid": 626,
    "name": "太吾绘卷",
    "cid": "games"
  },
  {
    "fid": 839,
    "name": "戴森球计划",
    "cid": "games"
  },
  {
    "fid": 414,
    "name": "饥荒",
    "cid": "games"
  },
  {
    "fid": 724,
    "name": "喷射战士",
    "cid": "games"
  },
  {
    "fid": 486,
    "name": "辐射",
    "cid": "games"
  },
  {
    "fid": 414,
    "name": "战神系列",
    "cid": "games"
  },
  {
    "fid": 414,
    "name": "古墓丽影",
    "cid": "games"
  },
  {
    "fid": 604,
    "name": "星露谷",
    "cid": "games"
  },
  {
    "fid": 523,
    "name": "全境封锁",
    "cid": "games"
  },
  {
    "fid": 414,
    "name": "战意/Conqueror\u2019s Blade",
    "cid": "games"
  },
  {
    "fid": 643,
    "name": "鬼泣5",
    "cid": "games"
  },
  {
    "fid": 730,
    "name": "游戏主播与UP主杂谈",
    "cid": "games"
  },
  {
    "fid": 561,
    "name": "尼尔系列",
    "cid": "games"
  },
  {
    "fid": 629,
    "name": "武侠/仙侠游戏综合",
    "cid": "games"
  },
  {
    "fid": 634,
    "name": "古剑奇谭",
    "cid": "games"
  },
  {
    "fid": -452227,
    "name": "精灵宝可梦",
    "cid": "games"
  },
  {
    "fid": 414,
    "name": "XCOM系列",
    "cid": "games"
  },
  {
    "fid": -5080470,
    "name": "流放之路",
    "cid": "games"
  },
  {
    "fid": 495,
    "name": "光荣策略游戏",
    "cid": "games"
  },
  {
    "fid": 796,
    "name": "永劫无间",
    "cid": "games"
  },
  {
    "fid": 414,
    "name": "十三机兵防卫圈",
    "cid": "games"
  },
  {
    "fid": 414,
    "name": "最终幻想系列",
    "cid": "games"
  },
  {
    "fid": 661,
    "name": "Paradox游戏综合讨论",
    "cid": "games"
  },
  {
    "fid": 630,
    "name": "全面战争系列",
    "cid": "games"
  },
  {
    "fid": 513,
    "name": "血源/黑暗之魂",
    "cid": "games"
  },
  {
    "fid": 414,
    "name": "游戏综合讨论区",
    "cid": "games"
  },
  {
    "fid": 414,
    "name": "游戏业界新闻",
    "cid": "games"
  },
  {
    "fid": 614,
    "name": "PS游戏综合讨论",
    "cid": "games"
  },
  {
    "fid": 615,
    "name": "XBOX游戏综合讨论",
    "cid": "games"
  },
  {
    "fid": 616,
    "name": "Nintendo游戏综合讨论",
    "cid": "games"
  },
  {
    "fid": 489,
    "name": "怪物猎人",
    "cid": "games"
  },
  {
    "fid": -21175563,
    "name": "传统RPG综合讨论",
    "cid": "games"
  },
  {
    "fid": 830,
    "name": "极限竞速:地平线 系列",
    "cid": "games"
  },
  {
    "fid": 414,
    "name": "从军/Enlisted",
    "cid": "games"
  },
  {
    "fid": 414,
    "name": "光环系列",
    "cid": "games"
  },
  {
    "fid": 414,
    "name": "超级马力欧奥德赛",
    "cid": "games"
  },
  {
    "fid": 416,
    "name": "火炬之光2",
    "cid": "games"
  },
  {
    "fid": 414,
    "name": "血污：夜之仪式",
    "cid": "games"
  },
  {
    "fid": 414,
    "name": "破坏领主",
    "cid": "games"
  },
  {
    "fid": 558,
    "name": "仁王系列",
    "cid": "games"
  },
  {
    "fid": 414,
    "name": "战锤:末世鼠疫",
    "cid": "games"
  },
  {
    "fid": 414,
    "name": "塞尔达传说",
    "cid": "games"
  },
  {
    "fid": 605,
    "name": "边缘世界",
    "cid": "games"
  },
  {
    "fid": 644,
    "name": "只狼 影逝二度",
    "cid": "games"
  },
  {
    "fid": 639,
    "name": "圣歌",
    "cid": "games"
  },
  {
    "fid": 552,
    "name": "Battlefield系列",
    "cid": "games"
  },
  {
    "fid": 414,
    "name": "战争机器",
    "cid": "games"
  },
  {
    "fid": 710,
    "name": "动物森友会",
    "cid": "games"
  },
  {
    "fid": 455,
    "name": "鬼武者 魂",
    "cid": "games"
  },
  {
    "fid": 628,
    "name": "荒野大镖客2",
    "cid": "games"
  },
  {
    "fid": 414,
    "name": "东方大战争",
    "cid": "games"
  },
  {
    "fid": 759,
    "name": "赛博朋克2077",
    "cid": "games"
  },
  {
    "fid": 414,
    "name": "女神异闻录",
    "cid": "games"
  },
  {
    "fid": 595,
    "name": "异度神剑",
    "cid": "games"
  },
  {
    "fid": 332,
    "name": "战锤40K",
    "cid": "games"
  },
  {
    "fid": 519,
    "name": "神秘海域",
    "cid": "games"
  },
  {
    "fid": 414,
    "name": "家园:卡拉克沙漠",
    "cid": "games"
  },
  {
    "fid": -534617,
    "name": "伊苏",
    "cid": "games"
  },
  {
    "fid": -4760591,
    "name": "侠客风云传",
    "cid": "games"
  },
  {
    "fid": 679,
    "name": "无主之地系列",
    "cid": "games"
  },
  {
    "fid": 831,
    "name": "艾尔登法环",
    "cid": "games"
  },
  {
    "fid": 709,
    "name": "足球经理2020",
    "cid": "games"
  },
  {
    "fid": -5951001,
    "name": "文明",
    "cid": "games"
  },
  {
    "fid": 627,
    "name": "刺客信条",
    "cid": "games"
  },
  {
    "fid": 600,
    "name": "彩虹六号:围攻",
    "cid": "games"
  },
  {
    "fid": 636,
    "name": "使命召唤系列",
    "cid": "games"
  },
  {
    "fid": 414,
    "name": "地平线:零之曙光",
    "cid": "games"
  },
  {
    "fid": 414,
    "name": "Grаnd Thеft Autо V",
    "cid": "games"
  },
  {
    "fid": 638,
    "name": "生化危机系列",
    "cid": "games"
  },
  {
    "fid": 414,
    "name": "碧蓝幻想 Versus",
    "cid": "games"
  },
  {
    "fid": 514,
    "name": "巫师3",
    "cid": "games"
  },
  {
    "fid": 705,
    "name": "任天堂明星大乱斗",
    "cid": "games"
  },
  {
    "fid": -38122457,
    "name": "炼金工房系列",
    "cid": "games"
  },
  {
    "fid": 300,
    "name": "逃离塔科夫",
    "cid": "games"
  },
  {
    "fid": 425,
    "name": "行星边际2",
    "cid": "games"
  },
  {
    "fid": 568,
    "name": "绝地求生",
    "cid": "games"
  },
  {
    "fid": 515,
    "name": "冒险岛2",
    "cid": "games"
  },
  {
    "fid": 618,
    "name": "古剑奇谭网络版",
    "cid": "games"
  },
  {
    "fid": 353,
    "name": "纽沃斯英雄传",
    "cid": "games"
  },
  {
    "fid": -38213667,
    "name": "万智牌",
    "cid": "games"
  },
  {
    "fid": 481,
    "name": "Minecraft",
    "cid": "games"
  },
  {
    "fid": -2371813,
    "name": "星战前夜",
    "cid": "games"
  },
  {
    "fid": 443,
    "name": "FIFA online 3",
    "cid": "games"
  },
  {
    "fid": -15219445,
    "name": "巫师之昆特牌",
    "cid": "games"
  },
  {
    "fid": 300,
    "name": "恐怖黎明",
    "cid": "games"
  },
  {
    "fid": 452,
    "name": "天涯明月刀",
    "cid": "games"
  },
  {
    "fid": -362960,
    "name": "最终幻想14",
    "cid": "games"
  },
  {
    "fid": 435,
    "name": "上古卷轴Online",
    "cid": "games"
  },
  {
    "fid": -46468,
    "name": "坦克世界",
    "cid": "games"
  },
  {
    "fid": 723,
    "name": "街头篮球",
    "cid": "games"
  },
  {
    "fid": 441,
    "name": "战舰世界",
    "cid": "games"
  },
  {
    "fid": 300,
    "name": "蓝色协议",
    "cid": "games"
  },
  {
    "fid": 640,
    "name": "Apex英雄",
    "cid": "games"
  },
  {
    "fid": 641,
    "name": "多多自走棋",
    "cid": "games"
  },
  {
    "fid": -2081117,
    "name": "游戏王",
    "cid": "games"
  },
  {
    "fid": 633,
    "name": "无限法则",
    "cid": "games"
  },
  {
    "fid": 707,
    "name": "冒险岛",
    "cid": "games"
  },
  {
    "fid": 611,
    "name": "逆水寒",
    "cid": "games"
  },
  {
    "fid": 603,
    "name": "星际战甲",
    "cid": "games"
  },
  {
    "fid": 609,
    "name": "堡垒之夜",
    "cid": "games"
  },
  {
    "fid": -47218,
    "name": "地下城与勇士",
    "cid": "games"
  },
  {
    "fid": 442,
    "name": "逆战",
    "cid": "games"
  },
  {
    "fid": -6194253,
    "name": "战争雷霆",
    "cid": "games"
  },
  {
    "fid": -235147,
    "name": "激战2:卓玛崛起",
    "cid": "games"
  },
  {
    "fid": 300,
    "name": "网络游戏综合",
    "cid": "games"
  },
  {
    "fid": 829,
    "name": "超激斗梦境",
    "cid": "games"
  },
  {
    "fid": 764,
    "name": "星际公民",
    "cid": "games"
  },
  {
    "fid": 300,
    "name": "神佑释放",
    "cid": "games"
  },
  {
    "fid": 300,
    "name": "New World新世界",
    "cid": "games"
  },
  {
    "fid": 300,
    "name": "帝国神话",
    "cid": "games"
  },
  {
    "fid": 300,
    "name": "Undecember",
    "cid": "games"
  },
  {
    "fid": 300,
    "name": "失落的方舟",
    "cid": "games"
  },
  {
    "fid": 650,
    "name": "原神",
    "cid": "games"
  },
  {
    "fid": -8180483,
    "name": "影之诗",
    "cid": "games"
  },
  {
    "fid": 454,
    "name": "神之浩劫",
    "cid": "games"
  },
  {
    "fid": 432,
    "name": "战机世界",
    "cid": "games"
  },
  {
    "fid": 563,
    "name": "命运",
    "cid": "games"
  },
  {
    "fid": 427,
    "name": "怪物猎人Online",
    "cid": "games"
  },
  {
    "fid": -7861121,
    "name": "剑网3",
    "cid": "games"
  },
  {
    "fid": 300,
    "name": "H1Z1:King of the Kill",
    "cid": "games"
  },
  {
    "fid": 444,
    "name": "刀塔传奇",
    "cid": "games"
  },
  {
    "fid": 428,
    "name": "刀剑乱舞",
    "cid": "games"
  },
  {
    "fid": 428,
    "name": "仙境传说:我的战术",
    "cid": "games"
  },
  {
    "fid": 428,
    "name": "剑网3:指尖江湖",
    "cid": "games"
  },
  {
    "fid": -103330,
    "name": "万象物语",
    "cid": "games"
  },
  {
    "fid": 428,
    "name": "从零开始的异世界生活-INFINITY",
    "cid": "games"
  },
  {
    "fid": 428,
    "name": "雷霆游戏",
    "cid": "games"
  },
  {
    "fid": 428,
    "name": "启源女神",
    "cid": "games"
  },
  {
    "fid": 428,
    "name": "东方大炮弹",
    "cid": "games"
  },
  {
    "fid": -60374520,
    "name": "食物语",
    "cid": "games"
  },
  {
    "fid": 428,
    "name": "神都夜行录",
    "cid": "games"
  },
  {
    "fid": 550,
    "name": "不思议迷宫",
    "cid": "games"
  },
  {
    "fid": 428,
    "name": "流星群侠传",
    "cid": "games"
  },
  {
    "fid": 447,
    "name": "锁链战记",
    "cid": "games"
  },
  {
    "fid": 428,
    "name": "开罗游戏",
    "cid": "games"
  },
  {
    "fid": 428,
    "name": "楚留香",
    "cid": "games"
  },
  {
    "fid": 732,
    "name": "江南百景图",
    "cid": "games"
  },
  {
    "fid": 641,
    "name": "多多自走棋",
    "cid": "games"
  },
  {
    "fid": 453,
    "name": "魔力宝贝",
    "cid": "games"
  },
  {
    "fid": 428,
    "name": "摩尔庄园",
    "cid": "games"
  },
  {
    "fid": -41374941,
    "name": "悠久之树",
    "cid": "games"
  },
  {
    "fid": 428,
    "name": "牧羊人之心",
    "cid": "games"
  },
  {
    "fid": 834,
    "name": "蔚蓝档案",
    "cid": "games"
  },
  {
    "fid": 428,
    "name": "无尽远征",
    "cid": "games"
  },
  {
    "fid": 836,
    "name": "幻塔",
    "cid": "games"
  },
  {
    "fid": 428,
    "name": "另一个伊甸",
    "cid": "games"
  },
  {
    "fid": 428,
    "name": "星战前夜：无烬星河",
    "cid": "games"
  },
  {
    "fid": 428,
    "name": "复苏的魔女",
    "cid": "games"
  },
  {
    "fid": 817,
    "name": "漫威对决",
    "cid": "games"
  },
  {
    "fid": 428,
    "name": "三国志幻想大陆",
    "cid": "games"
  },
  {
    "fid": 428,
    "name": "重返未来：1999",
    "cid": "games"
  },
  {
    "fid": 782,
    "name": "买断制手游",
    "cid": "games"
  },
  {
    "fid": 428,
    "name": "非人学园",
    "cid": "games"
  },
  {
    "fid": 428,
    "name": "手机/页游讨论",
    "cid": "games"
  },
  {
    "fid": 428,
    "name": "链战",
    "cid": "games"
  },
  {
    "fid": 571,
    "name": "手游评分版",
    "cid": "games"
  },
  {
    "fid": 428,
    "name": "苍之纪元",
    "cid": "games"
  },
  {
    "fid": 428,
    "name": "新游快讯",
    "cid": "games"
  },
  {
    "fid": 428,
    "name": "召唤与合成",
    "cid": "games"
  },
  {
    "fid": 428,
    "name": "版内活动",
    "cid": "games"
  },
  {
    "fid": 428,
    "name": "猎魂觉醒",
    "cid": "games"
  },
  {
    "fid": 823,
    "name": "上线游戏讨论区",
    "cid": "games"
  },
  {
    "fid": 428,
    "name": "旅行青蛙",
    "cid": "games"
  },
  {
    "fid": 822,
    "name": "测试阶段游戏讨论区",
    "cid": "games"
  },
  {
    "fid": 428,
    "name": "魔卡领域",
    "cid": "games"
  },
  {
    "fid": 824,
    "name": "海外游戏讨论区",
    "cid": "games"
  },
  {
    "fid": 428,
    "name": "QQ飞车",
    "cid": "games"
  },
  {
    "fid": 428,
    "name": "评测/安利",
    "cid": "games"
  },
  {
    "fid": 428,
    "name": "Kirara Fantasia",
    "cid": "games"
  },
  {
    "fid": 428,
    "name": "Counterside",
    "cid": "games"
  },
  {
    "fid": 428,
    "name": "苍蓝境界",
    "cid": "games"
  },
  {
    "fid": 428,
    "name": "偶像梦幻祭2",
    "cid": "games"
  },
  {
    "fid": 750,
    "name": "女性向游戏讨论",
    "cid": "games"
  },
  {
    "fid": -61285727,
    "name": "手游瓜事件",
    "cid": "games"
  },
  {
    "fid": 650,
    "name": "原神",
    "cid": "games"
  },
  {
    "fid": -34587507,
    "name": "明日方舟",
    "cid": "games"
  },
  {
    "fid": 540,
    "name": "Fate",
    "cid": "games"
  },
  {
    "fid": -8180483,
    "name": "影之诗",
    "cid": "games"
  },
  {
    "fid": 549,
    "name": "崩坏3",
    "cid": "games"
  },
  {
    "fid": 538,
    "name": "阴阳师",
    "cid": "games"
  },
  {
    "fid": 516,
    "name": "王者荣耀",
    "cid": "games"
  },
  {
    "fid": 564,
    "name": "碧蓝航线",
    "cid": "games"
  },
  {
    "fid": 428,
    "name": "荒野行动",
    "cid": "games"
  },
  {
    "fid": 428,
    "name": "想不想修真",
    "cid": "games"
  },
  {
    "fid": 428,
    "name": "questland",
    "cid": "games"
  },
  {
    "fid": 428,
    "name": "raziel",
    "cid": "games"
  },
  {
    "fid": 428,
    "name": "超进化物语",
    "cid": "games"
  },
  {
    "fid": 428,
    "name": "战舰联盟",
    "cid": "games"
  },
  {
    "fid": 428,
    "name": "荣耀战棋",
    "cid": "games"
  },
  {
    "fid": 428,
    "name": "喵星大作战",
    "cid": "games"
  },
  {
    "fid": 428,
    "name": "三国志曹操传",
    "cid": "games"
  },
  {
    "fid": 428,
    "name": "剑与家园",
    "cid": "games"
  },
  {
    "fid": 560,
    "name": "碧蓝幻想",
    "cid": "games"
  },
  {
    "fid": -40743354,
    "name": "赛马娘 Pretty Derby",
    "cid": "games"
  },
  {
    "fid": 812,
    "name": "哈利波特：魔法觉醒",
    "cid": "games"
  },
  {
    "fid": -10308342,
    "name": "公主连结Re:Dive",
    "cid": "games"
  },
  {
    "fid": 693,
    "name": "弹射世界",
    "cid": "games"
  },
  {
    "fid": 771,
    "name": "天地劫手游",
    "cid": "games"
  },
  {
    "fid": -547859,
    "name": "少女前线-16LAB研究院",
    "cid": "games"
  },
  {
    "fid": -60157311,
    "name": "少女前线：云图计划",
    "cid": "games"
  },
  {
    "fid": -373173,
    "name": "梦幻模拟战",
    "cid": "games"
  },
  {
    "fid": -7202235,
    "name": "舰队collection",
    "cid": "games"
  },
  {
    "fid": 428,
    "name": "召唤图板",
    "cid": "games"
  },
  {
    "fid": 428,
    "name": "晓之轨迹",
    "cid": "games"
  },
  {
    "fid": 428,
    "name": "地下城堡2",
    "cid": "games"
  },
  {
    "fid": 717,
    "name": "山海镜花",
    "cid": "games"
  },
  {
    "fid": 714,
    "name": "命运神界:梦境链接",
    "cid": "games"
  },
  {
    "fid": 678,
    "name": "家国梦",
    "cid": "games"
  },
  {
    "fid": 647,
    "name": "一起来捉妖",
    "cid": "games"
  },
  {
    "fid": 617,
    "name": "万王之王3D",
    "cid": "games"
  },
  {
    "fid": 598,
    "name": "为谁而炼金",
    "cid": "games"
  },
  {
    "fid": 569,
    "name": "死亡爱丽丝",
    "cid": "games"
  },
  {
    "fid": 696,
    "name": "战双帕弥什",
    "cid": "games"
  },
  {
    "fid": 642,
    "name": "第七史诗",
    "cid": "games"
  },
  {
    "fid": 779,
    "name": "坎特伯雷公主与骑士",
    "cid": "games"
  },
  {
    "fid": 623,
    "name": "失落的龙约",
    "cid": "games"
  },
  {
    "fid": 765,
    "name": "游戏王:决斗链接",
    "cid": "games"
  },
  {
    "fid": 803,
    "name": "白夜极光",
    "cid": "games"
  },
  {
    "fid": 593,
    "name": "决战！平安京",
    "cid": "games"
  },
  {
    "fid": -149110,
    "name": "战舰少女",
    "cid": "games"
  },
  {
    "fid": 757,
    "name": "时空中的绘旅人",
    "cid": "games"
  },
  {
    "fid": 695,
    "name": "阴阳师百闻牌",
    "cid": "games"
  },
  {
    "fid": 559,
    "name": "光明大陆",
    "cid": "games"
  },
  {
    "fid": 480,
    "name": "百万亚瑟王",
    "cid": "games"
  },
  {
    "fid": 428,
    "name": "英雄与冒险",
    "cid": "games"
  },
  {
    "fid": 426,
    "name": "智龙迷城",
    "cid": "games"
  },
  {
    "fid": -41232751,
    "name": "四叶草剧场",
    "cid": "games"
  },
  {
    "fid": 814,
    "name": "灵魂潮汐",
    "cid": "games"
  },
  {
    "fid": 751,
    "name": "未定事件簿",
    "cid": "games"
  },
  {
    "fid": 428,
    "name": "偶像大师",
    "cid": "games"
  },
  {
    "fid": 556,
    "name": "火焰之纹章Heroes",
    "cid": "games"
  },
  {
    "fid": 818,
    "name": "崩坏:星穹铁道",
    "cid": "games"
  },
  {
    "fid": 428,
    "name": "火影忍者-疾风传",
    "cid": "games"
  },
  {
    "fid": 795,
    "name": "机动战姬：聚变",
    "cid": "games"
  },
  {
    "fid": 664,
    "name": "BanG Dream!",
    "cid": "games"
  },
  {
    "fid": 701,
    "name": "剑与远征",
    "cid": "games"
  },
  {
    "fid": 692,
    "name": "天命之子",
    "cid": "games"
  },
  {
    "fid": 760,
    "name": "幻书启世录",
    "cid": "games"
  },
  {
    "fid": 555,
    "name": "仙境传说",
    "cid": "games"
  },
  {
    "fid": -51095,
    "name": "部落冲突",
    "cid": "games"
  },
  {
    "fid": 808,
    "name": "伊甸园的骄傲",
    "cid": "games"
  },
  {
    "fid": 492,
    "name": "部落冲突:皇室战争",
    "cid": "games"
  },
  {
    "fid": 726,
    "name": "荒野乱斗",
    "cid": "games"
  },
  {
    "fid": 691,
    "name": "双生视界",
    "cid": "games"
  },
  {
    "fid": 607,
    "name": "第五人格",
    "cid": "games"
  },
  {
    "fid": 625,
    "name": "圣斗士星矢",
    "cid": "games"
  },
  {
    "fid": -2068947,
    "name": "崩坏学园2",
    "cid": "games"
  },
  {
    "fid": 428,
    "name": "爱丽丝机甲",
    "cid": "games"
  },
  {
    "fid": -195362,
    "name": "少女前线2：追放",
    "cid": "games"
  },
  {
    "fid": 753,
    "name": "阴阳师妖怪屋",
    "cid": "games"
  },
  {
    "fid": 599,
    "name": "和平精英",
    "cid": "games"
  },
  {
    "fid": 551,
    "name": "克鲁赛德战记",
    "cid": "games"
  },
  {
    "fid": 772,
    "name": "忘川风华录",
    "cid": "games"
  },
  {
    "fid": -1513130,
    "name": "灰烬教会",
    "cid": "games"
  },
  {
    "fid": 816,
    "name": "无尽的拉格朗日",
    "cid": "games"
  },
  {
    "fid": 557,
    "name": "King&#39;s Raid",
    "cid": "games"
  },
  {
    "fid": 536,
    "name": "七雄战记",
    "cid": "games"
  },
  {
    "fid": 428,
    "name": "龙之谷",
    "cid": "games"
  },
  {
    "fid": 794,
    "name": "战争怒吼",
    "cid": "games"
  },
  {
    "fid": 755,
    "name": "解神者:X2",
    "cid": "games"
  },
  {
    "fid": 711,
    "name": "为美好的世界献上祝福！",
    "cid": "games"
  },
  {
    "fid": 689,
    "name": "魂器学院",
    "cid": "games"
  },
  {
    "fid": 662,
    "name": "重装战姬",
    "cid": "games"
  },
  {
    "fid": 428,
    "name": "率土之滨",
    "cid": "games"
  },
  {
    "fid": 494,
    "name": "魔龙之魂",
    "cid": "games"
  },
  {
    "fid": -37550969,
    "name": "魔法纪录",
    "cid": "games"
  },
  {
    "fid": 428,
    "name": "少女的王座",
    "cid": "games"
  },
  {
    "fid": 428,
    "name": "闪耀暖暖",
    "cid": "games"
  },
  {
    "fid": 428,
    "name": "狼人对决",
    "cid": "games"
  },
  {
    "fid": 428,
    "name": "怪物猎人Riders",
    "cid": "games"
  },
  {
    "fid": 428,
    "name": "永远的7日之都",
    "cid": "games"
  },
  {
    "fid": 428,
    "name": "七大罪:光与暗的交战",
    "cid": "games"
  },
  {
    "fid": 575,
    "name": "怪物弹珠",
    "cid": "games"
  },
  {
    "fid": 428,
    "name": "神代梦华谭",
    "cid": "games"
  },
  {
    "fid": 453,
    "name": "魔力宝贝",
    "cid": "games"
  },
  {
    "fid": 537,
    "name": "大航海时代5",
    "cid": "games"
  },
  {
    "fid": 420,
    "name": "我叫MT4",
    "cid": "games"
  },
  {
    "fid": 469,
    "name": "像素骑士团",
    "cid": "games"
  },
  {
    "fid": 601,
    "name": "晓之轨迹",
    "cid": "games"
  }
]